demo/__init__.py
demo/__main__.py
demo/add.py
demo/demo.py
demo/multiply.py
danieldemo-0.0.0.1.dist-info/LICENSE
danieldemo-0.0.0.1.dist-info/METADATA
danieldemo-0.0.0.1.dist-info/WHEEL
danieldemo-0.0.0.1.dist-info/top_level.txt
danieldemo-0.0.0.1.dist-info/RECORD
