Metadata-Version: 2.1
Name: danieldemo
Version: 0.0.0.1
Summary: Simple demo package
Home-page: https://google.com
Author: Daniel
License: UNKNOWN
Platform: UNKNOWN
Requires-Python: >=3.10
License-File: LICENSE
